whatType.py
whatType-0.0.1.dist-info/LICENSE
whatType-0.0.1.dist-info/METADATA
whatType-0.0.1.dist-info/WHEEL
whatType-0.0.1.dist-info/top_level.txt
whatType-0.0.1.dist-info/RECORD
